jwm/robotstxt/__init__.py
jwm/robotstxt/googlebot.cc
jwm/robotstxt/googlebot.cp310-win_amd64.pyd
jwm/robotstxt/googlebot.pyi
jwm.robotstxt-1.0.8.dist-info/LICENSE
jwm.robotstxt-1.0.8.dist-info/METADATA
jwm.robotstxt-1.0.8.dist-info/WHEEL
jwm.robotstxt-1.0.8.dist-info/top_level.txt
jwm.robotstxt-1.0.8.dist-info/RECORD
