Metadata-Version: 2.1
Name: jwm.robotstxt
Version: 1.0.8
Summary: Provides python access to Googles parser for robot.txt files as used by their GoogleBot webscraper.
Author-email: Joel Morley <jwmorley73@gmail.com>
License: MIT License
Project-URL: Homepage, https://github.com/jwmorley73/jwm.robotstxt
Project-URL: Documentation, https://jwmorley73.github.io/jwm.robotstxt/
Keywords: robotstxt,wrapper,google,parser
Classifier: License :: OSI Approved :: MIT License
Classifier: Programming Language :: Python
Classifier: Programming Language :: Python :: 3
Classifier: Programming Language :: Python :: 3 :: Only
Classifier: Programming Language :: Python :: 3.10
Classifier: Programming Language :: Python :: 3.11
Classifier: Programming Language :: Python :: 3.12
Classifier: Programming Language :: Python :: 3.13
Requires-Python: >=3.10
License-File: LICENSE
Provides-Extra: dev
Requires-Dist: jwm.robotstxt[doc,format,test] ; extra == 'dev'
Requires-Dist: cibuildwheel ; extra == 'dev'
Requires-Dist: setuptools ; extra == 'dev'
Requires-Dist: cmake ; extra == 'dev'
Requires-Dist: pybind11 ; extra == 'dev'
Provides-Extra: doc
Requires-Dist: sphinx ; extra == 'doc'
Requires-Dist: furo ; extra == 'doc'
Provides-Extra: format
Requires-Dist: isort ; extra == 'format'
Requires-Dist: black ; extra == 'format'
Requires-Dist: clang-format ; extra == 'format'
Provides-Extra: test
Requires-Dist: coverage ; extra == 'test'
Requires-Dist: pytest ; extra == 'test'
